sgnlp/__init__.py
sgnlp/models/__init__.py
sgnlp/models/coherence_momentum/__init__.py
sgnlp/models/coherence_momentum/config.py
sgnlp/models/coherence_momentum/modeling.py
sgnlp/models/coherence_momentum/preprocess.py
sgnlp/models/coherence_momentum/train.py
sgnlp/models/coherence_momentum/train_config.py
sgnlp/models/csgec/__init__.py
sgnlp/models/csgec/config.py
sgnlp/models/csgec/modeling.py
sgnlp/models/csgec/postprocess.py
sgnlp/models/csgec/preprocess.py
sgnlp/models/csgec/tokenization.py
sgnlp/models/csgec/utils.py
sgnlp/models/csgec/modules/__init__.py
sgnlp/models/csgec/modules/context_gate.py
sgnlp/models/csgec/modules/conv_attention.py
sgnlp/models/csgec/modules/conv_decoder.py
sgnlp/models/csgec/modules/conv_encoder.py
sgnlp/models/csgec/modules/conv_glu.py
sgnlp/models/csgec/modules/positional_embedding.py
sgnlp/models/emotion_entailment/__init__.py
sgnlp/models/emotion_entailment/config.py
sgnlp/models/emotion_entailment/data_class.py
sgnlp/models/emotion_entailment/eval.py
sgnlp/models/emotion_entailment/modeling.py
sgnlp/models/emotion_entailment/postprocess.py
sgnlp/models/emotion_entailment/preprocess.py
sgnlp/models/emotion_entailment/tokenization.py
sgnlp/models/emotion_entailment/train.py
sgnlp/models/emotion_entailment/utils.py
sgnlp/models/lif_3way_ap/__init__.py
sgnlp/models/lif_3way_ap/modeling.py
sgnlp/models/lif_3way_ap/modules/__init__.py
sgnlp/models/lif_3way_ap/modules/allennlp/__init__.py
sgnlp/models/lif_3way_ap/modules/allennlp/dataset_reader.py
sgnlp/models/lif_3way_ap/modules/allennlp/layers.py
sgnlp/models/lif_3way_ap/modules/allennlp/model.py
sgnlp/models/lif_3way_ap/modules/allennlp/predictor.py
sgnlp/models/lif_3way_ap/modules/allennlp/util.py
sgnlp/models/lsr/__init__.py
sgnlp/models/lsr/config.py
sgnlp/models/lsr/modeling.py
sgnlp/models/lsr/postprocess.py
sgnlp/models/lsr/preprocess.py
sgnlp/models/lsr/train.py
sgnlp/models/lsr/utils.py
sgnlp/models/lsr/modules/__init__.py
sgnlp/models/lsr/modules/attention.py
sgnlp-0.4.0.dist-info/LICENSE
sgnlp-0.4.0.dist-info/METADATA
sgnlp-0.4.0.dist-info/WHEEL
sgnlp-0.4.0.dist-info/top_level.txt
sgnlp-0.4.0.dist-info/RECORD
