Metadata-Version: 2.1
Name: sgnlp
Version: 0.4.0
Summary: Machine learning models from Singapore's NLP research community
Home-page: UNKNOWN
Author: Jonathan Heng, Raymond Ng, Zhi Chong Tan, Benedict Lee, Alon Tenzer
Author-email: sg-nlp@aisingapore.org
License: UNKNOWN
Keywords: NLP,machine learning,deep learning
Platform: UNKNOWN
Classifier: Programming Language :: Python :: 3
Requires-Python: >=3.7
Provides-Extra: lsr
Provides-Extra: lif_3way_ap
License-File: LICENSE
